brawlapi/Classes.py
brawlapi/DataBase.py
brawlapi/__init__.py
brawlapi/utils.py
brawlapi-0.1.13.dist-info/LICENSE
brawlapi-0.1.13.dist-info/METADATA
brawlapi-0.1.13.dist-info/WHEEL
brawlapi-0.1.13.dist-info/top_level.txt
brawlapi-0.1.13.dist-info/RECORD
