Metadata-Version: 2.1
Name: brawlapi
Version: 0.1.13
Summary: Description
Home-page: https://github.com/GaetanDesrues/brawl_api
Author: Gaetan Desrues
Author-email: gaetan.desrues@inria.fr
License: UNKNOWN
Platform: UNKNOWN
Classifier: Programming Language :: Python :: 3
Classifier: License :: OSI Approved :: MIT License
Classifier: Operating System :: OS Independent
